[
    {
        "name": "1",
        "type": "address"
    },
    {
        "name": "2",
        "type": "address"
    },
    {
        "name": "3",
        "type": "address"
    },
    {
        "name": "4",
        "type": "address"
    },
    {
        "name": "5",
        "type": "address"
    },
    {
        "name": "6",
        "type": "address"
    },
    {
        "name": "7",
        "type": "address"
    },
    {
        "name": "8",
        "type": "address"
    },
    {
        "name": "9",
        "type": "address"
    },
    {
        "name": "10",
        "type": "address"
    },
    {
        "name": "11",
        "type": "address"
    },
    {
        "name": "12",
        "type": "address"
    },
    {
        "name": "13",
        "type": "address"
    },
    {
        "name": "14",
        "type": "address"
    },
    {
        "name": "15",
        "type": "address"
    },
    {
        "name": "16",
        "type": "address"
    },
    {
        "name": "17",
        "type": "address"
    },
    {
        "name": "18",
        "type": "address"
    },
    {
        "name": "19",
        "type": "address"
    },
    {
        "name": "20",
        "type": "address"
    },
    {
        "name": "21",
        "type": "address"
    },
    {
        "name": "22",
        "type": "address"
    },
    {
        "name": "23",
        "type": "address"
    },
    {
        "name": "24",
        "type": "address"
    }
]